{"data":{"allMarkdownRemark":{"totalCount":2,"edges":[{"node":{"id":"14fa3120-fc70-5584-8e32-0058eb3f2e66","frontmatter":{"title":"Pandas and Bananas","date":"2017-08-21"},"excerpt":"Do Pandas eat bananas? Check out this short video that shows that yes! pandas do\nseem to really enjoy bananas!","html":"<p>Do Pandas eat bananas? Check out this short video that shows that yes! pandas do\nseem to really enjoy bananas!</p>\n<iframe width=\"560\" height=\"315\" src=\"https://www.youtube.com/embed/4SZl1r2O_bY\" frameborder=\"0\" allowfullscreen></iframe>","fields":{"slug":"/pandas-and-bananers/"}}},{"node":{"id":"b60a433d-054a-5715-a7e2-9d53e2202508","frontmatter":{"title":"Sweet pandas eating Sweets","date":"2017-08-10"},"excerpt":"Pandas are really sweet. Here's a video of a panda eating sweets.","html":"<p>Pandas are really sweet.</p>\n<p>Here's a video of a panda eating sweets.</p>\n<iframe width=\"560\" height=\"315\" src=\"https://www.youtube.com/embed/4n0xNbfJLR8\" frameborder=\"0\" allowfullscreen></iframe>","fields":{"slug":"/sweet-pandas-eating-sweets/"}}}]}},"pageContext":{}}